{"data":{"allMarkdownRemark":{"edges":[{"node":{"id":"2237491a-bbbf-5a34-9517-f12bce394819","frontmatter":{"id":"https://MuRongJs.github.io/javascript/es6/module02","url":"/javascript/es6/module02","title":"es6-module02","date":"2018/11/22 22:34:48","tags":["es6"],"headerImage":"","description":"es6-module02"}}},{"node":{"id":"a8025c59-98dd-534c-bb5f-7fa6d6de450b","frontmatter":{"id":"https://MuRongJs.github.io/javascript/es6/Decorator","url":"/javascript/es6/Decorator","title":"es6-Decorator","date":"2018/11/21 22:34:48","tags":["es6"],"headerImage":"","description":"es6-Decorator"}}},{"node":{"id":"850f2bb6-e29d-5a39-997a-00625c2ce0d7","frontmatter":{"id":"https://MuRongJs.github.io/javascript/es6/module01","url":"/javascript/es6/module01","title":"es6-module01","date":"2018/11/21 22:34:48","tags":["es6"],"headerImage":"","description":"es6-module01"}}},{"node":{"id":"639bb8f1-00c9-5c11-b5c2-60bbd1894906","frontmatter":{"id":"https://MuRongJs.github.io/javascript/es6/class","url":"/javascript/es6/class","title":"es6-class","date":"2018/11/19 22:34:48","tags":["es6"],"headerImage":"","description":"es6-class"}}},{"node":{"id":"5de56bbd-54b9-5450-9943-ac550c76d79a","frontmatter":{"id":"https://MuRongJs.github.io/javascript/es6/async","url":"/javascript/es6/async","title":"es6-async函数","date":"2018/11/16 22:34:48","tags":["es6","待修改"],"headerImage":"","description":"es6-async函数"}}},{"node":{"id":"3a2d11fd-2aeb-53a4-8f34-635b57f88c6f","frontmatter":{"id":"https://MuRongJs.github.io/javascript/es6/Generator","url":"/javascript/es6/Generator01","title":"es6-Generator","date":"2018/11/15 22:34:48","tags":["es6"],"headerImage":"","description":"es6-Generator"}}},{"node":{"id":"e2abce78-8d0f-5497-95e2-f87c1f2a5db7","frontmatter":{"id":"https://MuRongJs.github.io/javascript/es6/Generator","url":"/javascript/es6/Generator02","title":"es6-Generator","date":"2018/11/15 22:34:48","tags":["es6"],"headerImage":"","description":"es6-Generator"}}},{"node":{"id":"78b96251-1491-5d43-9338-ab96b1be500f","frontmatter":{"id":"https://MuRongJs.github.io/javascript/es6/Iterator","url":"/javascript/es6/Iterator","title":"es6-Iterator","date":"2018/11/14 22:34:48","tags":["es6"],"headerImage":"","description":"es6-Iterator"}}},{"node":{"id":"d0063cea-6966-5521-a285-aa0361210ea6","frontmatter":{"id":"https://MuRongJs.github.io/javascript/es6/Promise","url":"/javascript/es6/Promise","title":"es6-Promise","date":"2018/11/10 22:34:48","tags":["es6"],"headerImage":"","description":"es6-Promise"}}},{"node":{"id":"4d81d3a8-8de8-5e54-9ded-efe7d914a268","frontmatter":{"id":"https://MuRongJs.github.io/javascript/es6/Reflect","url":"/javascript/es6/Reflect","title":"es6-Reflect","date":"2018/10/27 22:34:48","tags":["es6"],"headerImage":"","description":"es6-Reflect"}}},{"node":{"id":"29496d9b-5f53-59f5-b8f1-b71a5750e756","frontmatter":{"id":"https://MuRongJs.github.io/javascript/es6/Proxy","url":"/javascript/es6/Proxy","title":"es6-Proxy","date":"2018/10/24 22:34:48","tags":["es6"],"headerImage":"","description":"es6-Proxy"}}},{"node":{"id":"dd87659a-86ef-54f4-8ed8-3ffd26f4c7a7","frontmatter":{"id":"https://MuRongJs.github.io/javascript/es6/Symbol","url":"/javascript/es6/Symbol","title":"es6-Symbol","date":"2018/10/22 22:34:48","tags":["es6"],"headerImage":"","description":"es6-Symbol"}}},{"node":{"id":"7750ee19-c5a7-5824-a1b5-75a31c5bca2f","frontmatter":{"id":"https://MuRongJs.github.io/javascript/es6/let&const","url":"/javascript/es6/let&const","title":"es6-let&const","date":"2018/10/22 22:34:48","tags":["es6"],"headerImage":"","description":"es6-let&const"}}},{"node":{"id":"d3985741-3c22-59ff-aac8-5f46877689b6","frontmatter":{"id":"https://MuRongJs.github.io/javascript/es6/set&map","url":"/javascript/es6/set&map","title":"es6-set&map","date":"2018/10/21 22:34:48","tags":["es6"],"headerImage":"","description":"es6-set&map"}}}]}},"pageContext":{"isCreatedByStatefulCreatePages":false,"tag":"es6"}}